haczechpkg/__init__.py
haczechpkg/top.py
haczechpkg/top_sub/__init__.py
haczechpkg/top_sub/sub/__init__.py
haczechpkg/top_sub/sub/sw/__init__.py
haczechpkg/top_sub/sub/sw/sub.py
haczechpkg-0.0.7.dist-info/METADATA
haczechpkg-0.0.7.dist-info/WHEEL
haczechpkg-0.0.7.dist-info/top_level.txt
haczechpkg-0.0.7.dist-info/RECORD
