Metadata-Version: 2.1
Name: haczechpkg
Version: 0.0.7
Summary: test pkg
Author: me
Author-email: me@me.me
Keywords: python,test_pkg
Classifier: Development Status :: 3 - Alpha
Classifier: Intended Audience :: Education
Classifier: Programming Language :: Python :: 2
Classifier: Programming Language :: Python :: 3
Classifier: Operating System :: MacOS :: MacOS X
Classifier: Operating System :: Microsoft :: Windows
